{
  "description": "A configurable fork of Transparent Top Bar for GNOME Shell with adjustable opacity, font, shadows, content colors, and overview behavior.",
  "name": "Transparent Top Bar Tweaks",
  "settings-schema": "org.gnome.shell.extensions.transparent-top-bar-tweaks",
  "shell-version": [
    "46",
    "47",
    "48",
    "49",
    "50"
  ],
  "url": "https://github.com/hectorandac/gnome-shell-extension-transparent-top-bar",
  "uuid": "transparent-top-bar-tweaks@hectorandac.github.io"
}
